csh_security/__init__.py
csh_security/authorizer.py
csh_security/user.py
comapsmarthome_security-0.0.7.dist-info/LICENSE
comapsmarthome_security-0.0.7.dist-info/METADATA
comapsmarthome_security-0.0.7.dist-info/WHEEL
comapsmarthome_security-0.0.7.dist-info/top_level.txt
comapsmarthome_security-0.0.7.dist-info/RECORD
