Metadata-Version: 2.1
Name: comapsmarthome-security
Version: 0.0.7
Summary: Security stuff for ComapSmartHome
Home-page: UNKNOWN
Author: Aurélien Sylvan
Author-email: aurelien.sylvan@comap.eu
License: UNKNOWN
Platform: UNKNOWN
Classifier: Programming Language :: Python :: 3
Classifier: License :: OSI Approved :: MIT License
Classifier: Operating System :: OS Independent
Requires-Dist: psycopg2-binary (>=2.8.0)
